designformat/__init__.py
designformat/address_map.py
designformat/base.py
designformat/block.py
designformat/command.py
designformat/command_field.py
designformat/common.py
designformat/connection.py
designformat/constant_tie.py
designformat/define.py
designformat/interconnect.py
designformat/port.py
designformat/project.py
designformat/register.py
designformat/register_group.py
designformat-1.3.dist-info/METADATA
designformat-1.3.dist-info/WHEEL
designformat-1.3.dist-info/top_level.txt
designformat-1.3.dist-info/RECORD
