Metadata-Version: 2.1
Name: designformat
Version: 1.3
Summary: A Cross-Language Interchange Format for Hardware Description Based on JSON
Home-page: https://www.bluwireless.com
Author: Blu Wireless Ltd
License: GNU General Public License v3.0
Project-URL: Source, https://github.com/bluwireless/designformat
Project-URL: Tracker, https://github.com/bluwireless/designformat/issues
Platform: UNKNOWN
Provides-Extra: documentation
Requires-Dist: sphinx ; extra == 'documentation'
Requires-Dist: recommonmark ; extra == 'documentation'
Requires-Dist: sphinx-markdown-tables ; extra == 'documentation'
Requires-Dist: sphinx-rtd-theme ; extra == 'documentation'
Requires-Dist: sphinx-js ; extra == 'documentation'
